{
    "$schema": "https://schema.management.azure.com/schemas/2015-01-01/deploymentTemplate.json#",
    "contentVersion": "1.0.0.0",
    "parameters": {
        "registryName": {
            "type": "string",
            "metadata": {
                "description": "The name of the container registry."
            }
        },
        "registrySku": {
            "type": "string",
            "defaultValue": "Basic",
            "metadata": {
                "description": "The SKU of the container registry."
            }
        },
        "adminUserEnabled": {
            "type": "bool",
            "defaultValue": false,
            "metadata": {
                "description": "The value that indicates whether the admin user is enabled."
            }
        },
        "principalId": {
            "type": "string",
            "metadata": {
              "description": "User name"
            }
        }
    },
    "variables": {
        "Contributor": "[concat('/subscriptions/',subscription().subscriptionId, '/providers/Microsoft.Authorization/roleDefinitions/', 'b24988ac-6180-42a0-ab88-20f7382dd24c')]",
    },
    "resources": [
        {
            "name": "[parameters('registryName')]",
            "type": "Microsoft.ContainerRegistry/registries",
            "location": "[resourceGroup().location]",
            "apiVersion": "2017-10-01",
            "sku": {
                "name": "[parameters('registrySku')]"
            },
            "properties": {
                "adminUserEnabled": "[parameters('adminUserEnabled')]"
            }
        },
        {
            "name": "[concat(parameters('registryName'),'-role')]",
            "type": "Microsoft.ContainerRegistry/registries/providers/roleAssignments",
            "location": "[resourceGroup().location]",
            "apiVersion": "2017-10-01",
            "dependsOn": [
                "[parameters('registryName')]"
            ],
            "properties": {
                "roleDefinitionId": "[variables('Contributor')]",
                "principalId": "[parameters('principalId')]"
            }
        }
    ]
}
